Dataviewer-0.4.8.data/scripts/viewer.bat
Dataviewer-0.4.8.data/scripts/viewer.py
dataviewer/__init__.py
dataviewer/dist/index.html
dataviewer/dist/css/app.9e227e1e.css
dataviewer/dist/css/app.b42e3a77.css
dataviewer/dist/css/chunk-vendors.02d743b0.css
dataviewer/dist/js/app.0335b7dc.js
dataviewer/dist/js/app.2254b81b.js
dataviewer/dist/js/app.71ee647b.js
dataviewer/dist/js/app.9adb08fd.js
dataviewer/dist/js/app.e9a742b9.js
dataviewer/dist/js/chunk-vendors.7ce398c7.js
dataviewer/dist/js/chunk-vendors.85233f08.js
Dataviewer-0.4.8.dist-info/LICENSE
Dataviewer-0.4.8.dist-info/METADATA
Dataviewer-0.4.8.dist-info/WHEEL
Dataviewer-0.4.8.dist-info/top_level.txt
Dataviewer-0.4.8.dist-info/RECORD
