Metadata-Version: 2.1
Name: Dataviewer
Version: 0.4.8
Summary: Dataviewer for project files
Home-page: https://gitlab.com/imdc/apps/dataviewer
Author: kdd
Author-email: kobededecker@gmail.com
License: GPL-3.0-or-later
Platform: UNKNOWN
Classifier: Programming Language :: Python
Classifier: Programming Language :: Python :: 2.7
Requires-Dist: Flask (==1.0.1)
Requires-Dist: Flask-Cors (==3.0.8)
